pabala/command.py
pabala/commands/build_package.py
pabala/consts.py
pabala/result.py
pabala-0.1.0.dist-info/METADATA
pabala-0.1.0.dist-info/WHEEL
pabala-0.1.0.dist-info/entry_points.txt
pabala-0.1.0.dist-info/RECORD
